covidlag.py
covidlag-0.0.8.dist-info/METADATA
covidlag-0.0.8.dist-info/WHEEL
covidlag-0.0.8.dist-info/entry_points.txt
covidlag-0.0.8.dist-info/top_level.txt
covidlag-0.0.8.dist-info/RECORD
