Metadata-Version: 2.1
Name: covidlag
Version: 0.0.8
Summary: lag time and case fatality rate (CFR)
Home-page: https://github.com/y-takefuji/covidlag
Author: yoshiyasu takefuji
Author-email: takefuji@keio.jp
License: UNKNOWN
Project-URL: Bug Tracker, https://github.com/y-takefuji/covidlag
Platform: UNKNOWN
Classifier: Programming Language :: Python :: 3
Classifier: License :: OSI Approved :: MIT License
Classifier: Operating System :: OS Independent
Requires-Python: >=3.8
